{"n_num": 3, "succs": [[2], [0, 2], []], "features": [[0, 0, 0, 1, 1, 0, 1], [0, 1, 1, 0, 4, 1, 2], [0, 1, 0, 0, 2, 1, 0]], "fname": "init_proc"}
{"n_num": 1, "succs": [[]], "features": [[0, 0, 0, 0, 1, 0, 0]], "fname": "free"}
{"n_num": 1, "succs": [[]], "features": [[0, 0, 0, 0, 1, 0, 0]], "fname": "abort"}
{"n_num": 1, "succs": [[]], "features": [[0, 0, 0, 0, 1, 0, 0]], "fname": "__errno_location"}
{"n_num": 1, "succs": [[]], "features": [[0, 0, 0, 0, 1, 0, 0]], "fname": "strncmp"}
{"n_num": 1, "succs": [[]], "features": [[0, 0, 0, 0, 1, 0, 0]], "fname": "_exit"}
{"n_num": 1, "succs": [[]], "features": [[0, 0, 0, 0, 1, 0, 0]], "fname": "__fpending"}
{"n_num": 1, "succs": [[]], "features": [[0, 0, 0, 0, 1, 0, 0]], "fname": "textdomain"}
{"n_num": 1, "succs": [[]], "features": [[0, 0, 0, 0, 1, 0, 0]], "fname": "fclose"}
{"n_num": 1, "succs": [[]], "features": [[0, 0, 0, 0, 1, 0, 0]], "fname": "bindtextdomain"}
{"n_num": 1, "succs": [[]], "features": [[0, 0, 0, 0, 1, 0, 0]], "fname": "__ctype_get_mb_cur_max"}
{"n_num": 1, "succs": [[]], "features": [[0, 0, 0, 0, 1, 0, 0]], "fname": "strlen"}
{"n_num": 1, "succs": [[]], "features": [[0, 0, 0, 0, 1, 0, 0]], "fname": "__stack_chk_fail"}
{"n_num": 1, "succs": [[]], "features": [[0, 0, 0, 0, 1, 0, 0]], "fname": "getopt_long"}
{"n_num": 1, "succs": [[]], "features": [[0, 0, 0, 0, 1, 0, 0]], "fname": "mbrtowc"}
{"n_num": 1, "succs": [[]], "features": [[0, 0, 0, 0, 1, 0, 0]], "fname": "gettext"}
{"n_num": 1, "succs": [[]], "features": [[0, 0, 0, 0, 1, 0, 0]], "fname": "printf"}
{"n_num": 1, "succs": [[]], "features": [[0, 0, 0, 0, 1, 0, 0]], "fname": "strrchr"}
{"n_num": 1, "succs": [[]], "features": [[0, 0, 0, 0, 1, 0, 0]], "fname": "lseek"}
{"n_num": 1, "succs": [[]], "features": [[0, 0, 0, 0, 1, 0, 0]], "fname": "memset"}
{"n_num": 1, "succs": [[]], "features": [[0, 0, 0, 0, 1, 0, 0]], "fname": "__libc_start_main"}
{"n_num": 1, "succs": [[]], "features": [[0, 0, 0, 0, 1, 0, 0]], "fname": "memcmp"}
{"n_num": 1, "succs": [[]], "features": [[0, 0, 0, 0, 1, 0, 0]], "fname": "fputs_unlocked"}
{"n_num": 1, "succs": [[]], "features": [[0, 0, 0, 0, 1, 0, 0]], "fname": "ferror_unlocked"}
{"n_num": 1, "succs": [[]], "features": [[0, 0, 0, 0, 1, 0, 0]], "fname": "calloc"}
{"n_num": 1, "succs": [[]], "features": [[0, 0, 0, 0, 1, 0, 0]], "fname": "strcmp"}
{"n_num": 1, "succs": [[]], "features": [[0, 0, 0, 0, 1, 0, 0]], "fname": "fprintf"}
{"n_num": 1, "succs": [[]], "features": [[0, 0, 0, 0, 1, 0, 0]], "fname": "mkfifo"}
{"n_num": 1, "succs": [[]], "features": [[0, 0, 0, 0, 1, 0, 0]], "fname": "umask"}
{"n_num": 1, "succs": [[]], "features": [[0, 0, 0, 0, 1, 0, 0]], "fname": "memcpy"}
{"n_num": 1, "succs": [[]], "features": [[0, 0, 0, 0, 1, 0, 0]], "fname": "fileno"}
{"n_num": 1, "succs": [[]], "features": [[0, 0, 0, 0, 1, 0, 0]], "fname": "__xstat"}
{"n_num": 1, "succs": [[]], "features": [[0, 0, 0, 0, 1, 0, 0]], "fname": "malloc"}
{"n_num": 1, "succs": [[]], "features": [[0, 0, 0, 0, 1, 0, 0]], "fname": "fflush"}
{"n_num": 1, "succs": [[]], "features": [[0, 0, 0, 0, 1, 0, 0]], "fname": "nl_langinfo"}
{"n_num": 1, "succs": [[]], "features": [[0, 0, 0, 0, 1, 0, 0]], "fname": "__freading"}
{"n_num": 1, "succs": [[]], "features": [[0, 0, 0, 0, 1, 0, 0]], "fname": "realloc"}
{"n_num": 1, "succs": [[]], "features": [[0, 0, 0, 0, 1, 0, 0]], "fname": "setlocale"}
{"n_num": 1, "succs": [[]], "features": [[0, 0, 0, 0, 1, 0, 0]], "fname": "chmod"}
{"n_num": 1, "succs": [[]], "features": [[0, 0, 0, 0, 1, 0, 0]], "fname": "error"}
{"n_num": 1, "succs": [[]], "features": [[0, 0, 0, 0, 1, 0, 0]], "fname": "fseeko"}
{"n_num": 1, "succs": [[]], "features": [[0, 0, 0, 0, 1, 0, 0]], "fname": "__cxa_atexit"}
{"n_num": 1, "succs": [[]], "features": [[0, 0, 0, 0, 1, 0, 0]], "fname": "exit"}
{"n_num": 1, "succs": [[]], "features": [[0, 0, 0, 0, 1, 0, 0]], "fname": "fwrite"}
{"n_num": 1, "succs": [[]], "features": [[0, 0, 0, 0, 1, 0, 0]], "fname": "mbsinit"}
{"n_num": 1, "succs": [[]], "features": [[0, 0, 0, 0, 1, 0, 0]], "fname": "iswprint"}
{"n_num": 1, "succs": [[]], "features": [[0, 0, 0, 0, 1, 0, 0]], "fname": "__ctype_b_loc"}
{"n_num": 1, "succs": [[]], "features": [[0, 0, 0, 0, 1, 0, 0]], "fname": "__gmon_start__"}
{"n_num": 1, "succs": [[]], "features": [[0, 4, 8, 1, 12, 0, 0]], "fname": "_start"}
{"n_num": 4, "succs": [[], [0, 2], [0, 3], []], "features": [[0, 0, 0, 0, 2, 0, 0], [0, 3, 3, 0, 6, 1, 3], [0, 1, 1, 0, 3, 0, 2], [0, 1, 1, 0, 3, 0, 0]], "fname": "deregister_tm_clones"}
{"n_num": 4, "succs": [[1, 2], [2, 3], [], []], "features": [[0, 5, 4, 0, 10, 5, 3], [0, 1, 1, 0, 3, 0, 2], [0, 0, 0, 0, 2, 0, 0], [0, 1, 1, 0, 3, 0, 0]], "fname": "register_tm_clones"}
{"n_num": 3, "succs": [[], [0, 2], [0]], "features": [[0, 0, 0, 0, 1, 0, 0], [0, 1, 0, 0, 2, 0, 2], [0, 1, 3, 1, 5, 0, 1]], "fname": "__do_global_dtors_aux"}
{"n_num": 5, "succs": [[3, 4], [0, 3], [], [2], [2]], "features": [[0, 1, 1, 0, 3, 0, 3], [0, 2, 1, 0, 3, 0, 4], [0, 0, 0, 0, 0, 0, 0], [0, 0, 0, 0, 1, 0, 1], [0, 0, 2, 1, 5, 0, 1]], "fname": "frame_dummy"}
{"n_num": 1, "succs": [[]], "features": [[0, 3, 7, 2, 15, 2, 0]], "fname": "emit_mandatory_arg_note"}
{"n_num": 15, "succs": [[], [0, 14], [6, 7], [2, 4], [2], [1], [9, 5], [8, 6], [6], [1], [13], [13], [3, 11], [3, 12], []], "features": [[0, 0, 0, 1, 1, 0, 0], [0, 2, 8, 2, 13, 0, 2], [1, 6, 8, 3, 13, 0, 8], [0, 0, 2, 0, 4, 0, 10], [0, 0, 3, 0, 3, 0, 9], [0, 1, 1, 0, 2, 0, 3], [1, 2, 8, 2, 12, 0, 5], [1, 1, 4, 1, 7, 0, 7], [0, 2, 6, 2, 8, 0, 6], [0, 1, 1, 0, 1, 0, 3], [6, 9, 24, 0, 27, 1, 14], [0, 1, 0, 0, 1, 1, 14], [0, 0, 5, 1, 8, 0, 14], [0, 0, 2, 0, 4, 0, 14], [0, 1, 0, 0, 4, 1, 0]], "fname": "emit_ancillary_info"}
{"n_num": 1, "succs": [[]], "features": [[0, 0, 4, 0, 6, 0, 0]], "fname": "se_const"}
{"n_num": 1, "succs": [[]], "features": [[0, 3, 6, 1, 10, 1, 0]], "fname": "defaultcon"}
{"n_num": 1, "succs": [[]], "features": [[0, 1, 4, 0, 6, 0, 0]], "fname": "smack_set_label_for_self"}
{"n_num": 1, "succs": [[]], "features": [[0, 1, 3, 0, 5, 0, 0]], "fname": "is_smack_enabled"}
{"n_num": 4, "succs": [[1, 2], [3], [3], []], "features": [[0, 2, 4, 0, 7, 1, 3], [0, 2, 8, 2, 11, 0, 1], [1, 7, 26, 14, 40, 0, 1], [0, 0, 2, 1, 3, 0, 0]], "fname": "usage"}
{"n_num": 39, "succs": [[9], [0, 9], [], [2, 6], [30], [18, 4], [16, 9], [20, 22], [21, 7], [24, 26], [17, 28], [10, 5], [], [19, 12], [8, 15], [8], [34, 27], [30], [], [18], [24], [20], [20, 23], [20], [14, 31], [24, 32], [25, 33], [1], [36, 30], [37, 38], [3, 29], [], [14], [25], [1], [30], [30], [], [11, 13]], "features": [[0, 3, 11, 4, 15, 0, 15], [0, 1, 0, 0, 2, 0, 16], [0, 5, 6, 3, 9, 0, 0], [0, 0, 1, 0, 3, 0, 22], [0, 0, 2, 0, 3, 0, 38], [0, 1, 0, 0, 2, 0, 38], [0, 1, 0, 0, 2, 0, 20], [0, 1, 0, 0, 2, 0, 10], [0, 0, 7, 1, 12, 1, 10], [0, 2, 1, 0, 3, 0, 14], [0, 0, 0, 1, 3, 0, 38], [0, 1, 0, 0, 2, 0, 38], [1, 5, 10, 2, 12, 0, 0], [0, 1, 0, 0, 2, 0, 3], [0, 1, 0, 0, 2, 0, 10], [0, 1, 6, 1, 9, 1, 10], [0, 1, 1, 1, 4, 0, 19], [0, 0, 2, 0, 3, 0, 38], [0, 1, 1, 1, 2, 0, 0], [0, 0, 0, 0, 1, 0, 1], [0, 1, 2, 0, 3, 1, 10], [0, 5, 16, 4, 23, 1, 10], [0, 0, 7, 1, 12, 1, 10], [0, 5, 16, 4, 22, 1, 10], [0, 0, 1, 0, 3, 0, 10], [0, 4, 15, 4, 21, 0, 11], [0, 1, 3, 1, 6, 0, 13], [0, 0, 3, 1, 5, 0, 17], [0, 0, 1, 0, 3, 0, 38], [0, 1, 1, 0, 3, 0, 38], [1, 3, 7, 1, 10, 0, 38], [0, 1, 1, 0, 6, 1, 0], [0, 4, 5, 2, 7, 0, 10], [0, 4, 5, 2, 7, 0, 12], [0, 0, 4, 2, 6, 0, 17], [3, 8, 19, 5, 26, 1, 38], [0, 4, 5, 2, 8, 0, 38], [0, 1, 1, 1, 2, 0, 0], [0, 1, 0, 0, 2, 0, 38]], "fname": "main"}
{"n_num": 1, "succs": [[]], "features": [[0, 0, 5, 0, 8, 0, 0]], "fname": "close_stdout_set_file_name"}
{"n_num": 1, "succs": [[]], "features": [[0, 0, 6, 0, 9, 0, 0]], "fname": "close_stdout_set_ignore_EPIPE"}
{"n_num": 10, "succs": [[9, 7], [0, 9], [1, 7], [], [3], [3], [], [8, 6], [], [4, 5]], "features": [[0, 1, 1, 1, 4, 0, 7], [0, 1, 1, 0, 4, 0, 8], [0, 1, 5, 1, 9, 1, 9], [0, 0, 2, 1, 3, 0, 0], [0, 3, 11, 3, 15, 0, 1], [0, 3, 7, 2, 9, 0, 1], [0, 0, 2, 1, 3, 0, 0], [0, 0, 2, 1, 5, 0, 2], [0, 1, 0, 0, 5, 1, 0], [0, 1, 3, 1, 6, 0, 3]], "fname": "close_stdout"}
{"n_num": 1, "succs": [[]], "features": [[0, 0, 4, 0, 6, 0, 0]], "fname": "octal_to_mode"}
{"n_num": 1, "succs": [[]], "features": [[0, 7, 21, 1, 26, 2, 0]], "fname": "make_node_op_equals"}
{"n_num": 82, "succs": [[2], [0, 3, 4, 5, 6, 7, 8], [9], [2], [2], [2], [2], [2], [68], [8, 1], [68], [10, 52], [58, 29], [67, 12], [54], [14], [14], [14], [14], [80], [19, 55], [55], [43, 21], [45], [25, 23], [45], [69, 55], [26, 69], [68], [64, 28], [44, 29], [29, 30], [42, 22], [22], [46], [73, 34], [40], [66, 36], [16, 57], [38, 15], [54], [40], [27, 55], [32, 42], [41, 20], [80], [29, 31], [65, 53], [72, 47], [47], [9], [50, 60], [50], [80], [18, 13], [80], [55], [55], [59, 29], [56, 29], [33], [37], [61, 63], [49, 61], [74, 51], [48, 72], [78, 71], [17, 39], [35, 77], [68], [68], [76, 78], [24, 75], [46], [11, 70], [80], [78, 79], [46], [81], [81], [], [37]], "features": [[0, 1, 0, 0, 2, 0, 60], [0, 0, 2, 0, 3, 0, 60], [0, 1, 0, 0, 2, 1, 60], [0, 1, 0, 0, 2, 0, 60], [0, 1, 0, 0, 2, 0, 60], [0, 1, 0, 0, 2, 0, 60], [0, 1, 1, 0, 2, 0, 60], [0, 1, 0, 0, 2, 0, 60], [0, 0, 0, 0, 1, 0, 60], [0, 2, 3, 0, 6, 1, 60], [0, 2, 1, 0, 3, 1, 60], [0, 1, 0, 0, 2, 0, 60], [0, 1, 0, 0, 2, 0, 60], [0, 1, 0, 0, 2, 0, 60], [0, 1, 0, 0, 2, 1, 60], [0, 1, 0, 0, 2, 0, 60], [0, 1, 0, 0, 2, 0, 60], [0, 1, 0, 0, 2, 0, 60], [0, 1, 0, 0, 1, 0, 60], [0, 2, 5, 0, 8, 2, 1], [0, 0, 2, 0, 5, 0, 3], [0, 0, 0, 0, 1, 0, 2], [0, 2, 8, 0, 12, 2, 60], [0, 2, 2, 0, 4, 0, 2], [0, 1, 6, 1, 10, 1, 4], [0, 1, 1, 0, 1, 0, 2], [0, 1, 2, 0, 4, 0, 60], [0, 0, 2, 0, 4, 0, 60], [0, 2, 1, 0, 3, 1, 60], [0, 3, 10, 0, 12, 0, 60], [0, 1, 2, 0, 4, 0, 60], [0, 1, 2, 0, 4, 0, 60], [0, 1, 2, 0, 4, 0, 60], [0, 1, 1, 0, 1, 0, 60], [0, 0, 1, 0, 2, 0, 60], [0, 1, 0, 0, 2, 0, 60], [0, 1, 6, 1, 7, 0, 60], [0, 0, 2, 0, 4, 0, 68], [0, 1, 0, 0, 2, 0, 60], [0, 1, 0, 0, 2, 0, 60], [0, 1, 1, 0, 1, 0, 60], [0, 1, 0, 0, 2, 1, 60], [0, 1, 0, 0, 2, 0, 60], [0, 1, 2, 0, 4, 0, 60], [0, 1, 2, 0, 4, 0, 60], [0, 0, 5, 1, 7, 0, 1], [0, 1, 4, 0, 6, 0, 60], [0, 2, 8, 0, 12, 2, 11], [0, 1, 2, 0, 4, 0, 11], [0, 1, 3, 0, 3, 0, 11], [0, 2, 2, 0, 2, 0, 60], [0, 2, 0, 0, 3, 1, 60], [0, 0, 0, 0, 1, 0, 60], [0, 1, 1, 0, 2, 0, 1], [0, 1, 3, 0, 5, 0, 60], [0, 1, 3, 1, 4, 0, 1], [0, 0, 0, 0, 1, 0, 2], [0, 0, 0, 0, 1, 0, 2], [0, 1, 0, 0, 2, 0, 60], [0, 1, 0, 0, 2, 0, 60], [0, 0, 0, 0, 1, 0, 60], [0, 1, 3, 0, 4, 0, 68], [0, 3, 6, 0, 9, 1, 81], [0, 1, 2, 0, 4, 0, 80], [0, 1, 0, 0, 2, 0, 60], [0, 1, 2, 0, 4, 0, 11], [0, 1, 2, 0, 4, 0, 68], [0, 1, 0, 0, 2, 0, 60], [0, 2, 18, 0, 22, 2, 60], [0, 2, 7, 1, 9, 0, 60], [0, 2, 1, 0, 3, 1, 60], [0, 1, 2, 0, 4, 0, 68], [0, 0, 2, 0, 4, 0, 6], [0, 0, 2, 0, 3, 0, 60], [0, 1, 0, 0, 2, 0, 60], [0, 1, 1, 0, 2, 0, 1], [0, 1, 2, 0, 4, 0, 68], [0, 0, 1, 0, 1, 0, 60], [0, 1, 1, 0, 2, 0, 68], [0, 1, 1, 0, 1, 0, 68], [0, 0, 0, 0, 2, 0, 0], [0, 1, 0, 0, 3, 2, 68]], "fname": "mode_compile"}
{"n_num": 6, "succs": [[1, 3], [2], [4, 5], [2], [], []], "features": [[0, 1, 9, 1, 14, 1, 5], [0, 1, 1, 0, 2, 0, 3], [0, 0, 1, 0, 3, 0, 2], [0, 1, 3, 1, 4, 0, 3], [0, 0, 0, 1, 1, 0, 0], [0, 0, 0, 0, 2, 0, 0]], "fname": "mode_create_from_ref"}
{"n_num": 38, "succs": [[15], [0, 3], [8], [15], [12], [4, 6], [12], [13, 14], [32, 7], [26], [9, 31], [16], [17, 11], [21], [21], [26], [24], [16], [26], [18, 27], [22, 23], [20, 29], [23], [24], [28, 30], [24], [8], [26], [10], [25, 33], [10], [1, 19], [34, 37], [35, 36], [37], [5], [5], []], "features": [[0, 0, 1, 0, 3, 0, 37], [0, 1, 0, 0, 2, 0, 37], [0, 2, 12, 0, 13, 0, 37], [0, 1, 1, 0, 1, 0, 37], [0, 1, 1, 0, 2, 0, 37], [0, 1, 2, 0, 4, 0, 37], [0, 1, 1, 0, 1, 0, 37], [0, 1, 3, 0, 5, 0, 37], [0, 0, 2, 0, 4, 0, 37], [0, 0, 3, 0, 6, 0, 37], [0, 1, 6, 0, 9, 0, 37], [0, 1, 1, 0, 2, 0, 37], [0, 1, 2, 0, 5, 0, 37], [0, 1, 1, 0, 1, 0, 37], [0, 1, 1, 0, 2, 0, 37], [0, 1, 6, 0, 11, 0, 37], [0, 0, 0, 0, 3, 0, 37], [0, 1, 1, 0, 1, 0, 37], [0, 0, 2, 0, 5, 0, 37], [0, 1, 0, 0, 2, 0, 37], [0, 1, 4, 0, 7, 0, 37], [0, 1, 10, 0, 13, 0, 37], [0, 1, 0, 0, 1, 0, 37], [0, 0, 0, 0, 1, 0, 37], [0, 1, 0, 0, 2, 0, 37], [0, 1, 0, 0, 2, 0, 37], [0, 1, 0, 0, 1, 1, 37], [0, 0, 0, 0, 1, 0, 37], [0, 0, 1, 0, 3, 0, 37], [0, 1, 0, 0, 2, 0, 37], [0, 0, 1, 0, 1, 0, 37], [0, 1, 0, 0, 2, 0, 37], [0, 1, 0, 0, 2, 0, 2], [0, 1, 4, 0, 6, 0, 37], [0, 0, 3, 0, 3, 0, 1], [0, 1, 1, 0, 2, 0, 37], [0, 1, 1, 0, 1, 0, 37], [0, 0, 1, 0, 3, 0, 0]], "fname": "mode_adjust"}
{"n_num": 10, "succs": [[1, 6], [], [8, 7], [8, 2], [3], [3], [4, 5], [8, 9], [], [8]], "features": [[0, 2, 3, 0, 6, 1, 9], [0, 3, 5, 2, 7, 0, 0], [1, 2, 4, 1, 8, 1, 3], [0, 1, 4, 0, 7, 1, 4], [0, 1, 1, 0, 3, 1, 5], [0, 0, 1, 0, 1, 0, 5], [0, 2, 4, 1, 7, 0, 7], [1, 1, 6, 1, 9, 0, 2], [0, 0, 4, 0, 7, 0, 0], [0, 1, 4, 0, 5, 1, 1]], "fname": "set_program_name"}
{"n_num": 4, "succs": [[2], [0, 3], [], [2]], "features": [[0, 0, 1, 0, 2, 0, 1], [0, 2, 5, 1, 9, 1, 3], [0, 1, 7, 2, 11, 0, 0], [0, 1, 1, 0, 1, 0, 1]], "fname": "clone_quoting_options"}
{"n_num": 4, "succs": [[1, 3], [2], [], [2]], "features": [[0, 1, 3, 0, 5, 0, 3], [0, 1, 1, 0, 1, 0, 1], [0, 0, 1, 0, 3, 0, 0], [0, 0, 1, 0, 2, 0, 1]], "fname": "get_quoting_style"}
{"n_num": 4, "succs": [[2, 3], [], [1], [1]], "features": [[0, 1, 4, 0, 6, 0, 3], [0, 0, 2, 0, 5, 0, 0], [0, 0, 1, 0, 2, 0, 1], [0, 1, 1, 0, 1, 0, 1]], "fname": "set_quoting_style"}
{"n_num": 4, "succs": [[3], [0, 2], [3], []], "features": [[0, 0, 1, 0, 2, 0, 1], [0, 1, 8, 0, 10, 0, 3], [0, 1, 1, 0, 1, 0, 1], [0, 5, 25, 0, 34, 5, 0]], "fname": "set_char_quoting"}
{"n_num": 3, "succs": [[2], [0, 2], []], "features": [[0, 1, 1, 0, 1, 0, 1], [0, 1, 4, 0, 6, 0, 2], [0, 0, 7, 0, 9, 0, 0]], "fname": "set_quoting_flags"}
{"n_num": 6, "succs": [[2], [0, 2], [4, 5], [], [3, 5], []], "features": [[0, 1, 1, 0, 1, 0, 4], [0, 2, 5, 0, 8, 1, 5], [0, 2, 2, 0, 4, 0, 3], [0, 0, 6, 0, 9, 0, 0], [0, 1, 0, 0, 2, 0, 2], [0, 0, 0, 1, 1, 0, 0]], "fname": "set_custom_quoting"}
{"n_num": 5, "succs": [[], [0, 4], [1, 3], [], []], "features": [[0, 0, 0, 0, 2, 0, 0], [0, 0, 19, 0, 21, 0, 2], [0, 4, 11, 0, 15, 1, 4], [0, 0, 0, 1, 1, 0, 0], [0, 0, 0, 1, 1, 0, 0]], "fname": "quoting_options_from_style"}
{"n_num": 14, "succs": [[2], [0, 11], [], [2], [2], [2], [2], [2], [2], [5, 6], [3, 4], [10, 13], [8, 7], [9, 12]], "features": [[0, 0, 1, 0, 2, 0, 1], [0, 1, 8, 1, 12, 1, 13], [0, 0, 0, 0, 2, 0, 0], [0, 1, 1, 0, 2, 0, 1], [0, 1, 1, 0, 2, 0, 1], [0, 1, 1, 0, 2, 0, 1], [0, 1, 1, 0, 2, 0, 1], [0, 1, 1, 0, 2, 0, 1], [0, 1, 1, 0, 1, 0, 1], [0, 1, 2, 0, 4, 0, 3], [0, 1, 2, 0, 4, 0, 3], [1, 0, 4, 2, 8, 0, 11], [0, 1, 0, 0, 2, 0, 3], [1, 0, 3, 1, 6, 0, 7]], "fname": "gettext_quote"}
{"n_num": 279, "succs": [[36, 21], [0, 76], [42, 46], [2, 67], [22], [224, 4, 264, 265, 138, 271, 273, 24, 61], [68], [68, 6], [], [8, 5], [74, 100], [10, 12], [10, 262], [10], [20, 30], [30, 14], [81, 34], [16, 124], [107], [192, 18], [149, 30], [36], [93], [22], [22], [22], [22], [134, 15], [97], [97, 28], [50, 35], [30], [30], [30], [81], [50, 150], [64, 65], [140, 191], [37, 39], [140, 37], [184, 62], [40, 132], [170, 7], [42, 44], [42, 45], [42, 3], [112, 42], [111], [99, 47], [255], [49, 70], [50], [50], [50], [50], [84, 63], [215, 55], [255], [57], [57], [174, 175], [60, 23], [184, 75], [226], [76], [64], [275, 244], [66], [66], [66], [19], [234, 255], [255, 71], [104], [104, 73], [184, 89], [247], [76, 78], [76, 79], [1, 76], [88], [80, 88], [29, 7], [95], [121, 83], [32, 33, 98, 51, 243, 126, 110, 48, 241, 115, 52, 53, 54, 87, 27, 158, 31], [90, 247], [205, 86], [91, 102], [116, 92], [94], [102], [114, 116], [242, 237], [93], [217, 117], [95], [82], [101, 109], [111], [74], [58, 122], [124], [119], [119, 103], [9], [108, 69], [106, 69], [69], [113, 258], [115, 251], [250, 110], [9], [107], [120], [126], [120], [96, 118], [217], [180], [160, 184], [203, 127], [145, 59], [148], [123, 148], [252, 135], [252, 125], [203, 141], [177, 196], [128, 165], [159, 151], [130, 180], [178, 43], [146], [163, 133], [107], [107], [136, 168], [61], [146], [19, 139], [153], [82], [107], [222, 143], [169, 59], [209, 167], [146], [146], [146], [107], [159], [155, 182], [152, 203], [107], [154, 182], [107], [11, 156], [129, 253], [180], [184, 137], [107], [161, 43], [107], [107], [107], [176, 188], [209, 166], [184], [59, 190], [142, 7], [253], [171, 173], [171], [175], [23], [188], [196, 183], [162, 43], [225, 181], [179, 147], [225, 189], [153], [196], [243, 85], [56, 187], [56, 213], [56], [195, 204], [208, 207], [268, 199], [19, 140], [17, 124], [219], [193, 219], [204], [211, 206], [131, 157], [131, 197], [144, 268], [94], [200, 94], [186], [202, 186], [209], [210, 164], [211], [218, 212], [207], [216, 201], [260, 214], [172, 220], [218], [226], [260, 221], [226], [201], [226], [225], [13, 278], [172], [232, 227], [233, 228], [229], [229, 223], [238, 230], [72, 234], [232], [233], [25, 231], [238], [236], [246, 239], [240, 248], [198], [249, 245], [25, 235], [41], [198], [246], [248], [255], [41], [185, 261], [], [249], [257, 254], [255], [256, 259], [236], [255], [255], [255], [255], [257], [38, 39], [259], [260], [255], [267, 263], [77, 270], [226], [266, 194], [267], [265], [271], [194], [269], [269], [59], [77], [272, 273], [273], [274, 26], [276, 277], [], [277], [26], [13]], "features": [[0, 0, 1, 0, 3, 0, 278], [0, 1, 4, 0, 7, 1, 278], [0, 1, 0, 0, 2, 0, 278], [0, 1, 0, 0, 2, 0, 278], [0, 1, 1, 0, 2, 0, 278], [0, 0, 2, 0, 3, 0, 278], [0, 1, 3, 0, 4, 1, 4], [0, 0, 1, 0, 3, 0, 5], [0, 0, 0, 1, 1, 0, 0], [0, 1, 0, 0, 2, 0, 278], [0, 0, 1, 0, 3, 0, 278], [0, 2, 1, 0, 3, 0, 278], [0, 1, 1, 0, 4, 0, 278], [0, 2, 1, 0, 2, 1, 278], [0, 1, 0, 0, 2, 0, 278], [0, 1, 0, 0, 2, 0, 278], [0, 0, 1, 0, 3, 0, 278], [0, 1, 1, 0, 4, 0, 278], [0, 0, 0, 0, 2, 0, 7], [0, 1, 0, 0, 2, 0, 278], [0, 1, 0, 0, 2, 0, 278], [0, 1, 3, 0, 4, 1, 278], [0, 1, 1, 0, 2, 0, 278], [0, 3, 3, 0, 4, 0, 278], [0, 2, 2, 0, 3, 0, 278], [0, 1, 6, 1, 8, 0, 278], [0, 2, 2, 0, 3, 0, 278], [0, 1, 2, 0, 4, 0, 278], [0, 0, 5, 0, 6, 1, 10], [0, 0, 1, 0, 3, 0, 10], [0, 1, 0, 0, 2, 0, 278], [0, 1, 1, 0, 2, 0, 278], [0, 1, 1, 0, 2, 0, 278], [0, 1, 1, 0, 2, 0, 278], [0, 1, 3, 0, 4, 1, 278], [0, 1, 0, 0, 2, 0, 278], [0, 1, 1, 0, 4, 1, 278], [0, 1, 0, 0, 2, 0, 278], [0, 1, 0, 0, 2, 0, 278], [0, 1, 1, 0, 4, 0, 278], [0, 4, 3, 0, 5, 0, 278], [0, 0, 0, 0, 2, 0, 278], [0, 1, 0, 0, 2, 0, 12], [0, 1, 0, 0, 2, 0, 278], [0, 1, 1, 0, 4, 0, 278], [0, 1, 0, 0, 2, 0, 278], [0, 1, 0, 0, 2, 0, 278], [0, 1, 2, 0, 6, 1, 278], [0, 1, 0, 0, 2, 0, 278], [0, 0, 0, 0, 2, 0, 278], [0, 1, 0, 0, 2, 0, 278], [0, 1, 1, 0, 2, 0, 278], [0, 1, 1, 0, 2, 0, 278], [0, 1, 1, 0, 2, 0, 278], [0, 1, 1, 0, 2, 0, 278], [0, 1, 0, 0, 2, 0, 278], [0, 1, 14, 1, 20, 3, 278], [0, 0, 0, 0, 1, 0, 278], [0, 0, 0, 0, 1, 0, 278], [0, 0, 0, 0, 1, 0, 278], [0, 0, 1, 0, 3, 0, 278], [0, 1, 1, 0, 4, 0, 278], [0, 1, 0, 0, 2, 0, 278], [0, 1, 1, 0, 2, 0, 278], [0, 1, 0, 0, 1, 1, 278], [0, 1, 3, 0, 4, 1, 278], [0, 0, 1, 0, 3, 0, 2], [0, 3, 11, 1, 15, 2, 3], [0, 0, 1, 0, 2, 0, 3], [0, 4, 14, 1, 17, 2, 3], [0, 0, 2, 0, 3, 0, 278], [0, 1, 1, 0, 4, 0, 278], [0, 1, 0, 0, 2, 0, 278], [0, 2, 4, 0, 7, 3, 278], [0, 1, 1, 0, 4, 1, 278], [0, 1, 0, 0, 2, 0, 278], [0, 1, 1, 0, 2, 0, 278], [0, 2, 0, 0, 3, 1, 278], [0, 1, 1, 0, 4, 1, 278], [0, 1, 4, 0, 7, 1, 278], [0, 1, 3, 0, 4, 1, 278], [0, 1, 1, 0, 4, 1, 278], [0, 0, 2, 0, 4, 0, 10], [0, 1, 1, 0, 2, 0, 278], [0, 1, 0, 0, 2, 0, 278], [0, 0, 2, 0, 3, 0, 278], [0, 1, 2, 0, 4, 0, 278], [0, 1, 0, 0, 2, 0, 278], [0, 1, 1, 0, 4, 1, 278], [0, 1, 3, 0, 5, 0, 278], [0, 0, 0, 0, 1, 0, 278], [0, 1, 3, 0, 4, 1, 278], [0, 1, 0, 0, 2, 0, 278], [0, 1, 0, 0, 2, 0, 278], [0, 1, 0, 0, 1, 1, 278], [0, 0, 2, 0, 5, 1, 278], [0, 1, 0, 0, 1, 1, 278], [0, 2, 0, 0, 2, 2, 10], [0, 1, 1, 0, 3, 0, 278], [0, 1, 0, 0, 2, 0, 278], [0, 1, 3, 0, 4, 1, 278], [0, 1, 0, 0, 2, 0, 278], [0, 2, 1, 0, 2, 1, 278], [0, 3, 5, 0, 8, 3, 278], [0, 1, 1, 0, 4, 1, 278], [0, 11, 29, 1, 36, 1, 278], [0, 1, 0, 0, 2, 0, 5], [0, 1, 0, 0, 2, 0, 6], [0, 1, 1, 0, 1, 0, 4], [0, 1, 0, 0, 2, 0, 278], [0, 1, 0, 0, 2, 0, 278], [0, 0, 0, 0, 2, 0, 278], [0, 1, 3, 0, 4, 0, 278], [0, 0, 0, 0, 1, 0, 7], [0, 0, 4, 1, 6, 0, 278], [0, 1, 1, 0, 1, 0, 278], [0, 0, 1, 0, 1, 0, 278], [0, 0, 4, 0, 8, 2, 278], [0, 0, 0, 0, 1, 0, 278], [0, 3, 3, 0, 6, 2, 278], [0, 0, 0, 0, 2, 0, 278], [0, 1, 0, 0, 2, 0, 278], [0, 1, 2, 0, 4, 0, 278], [0, 1, 3, 0, 4, 1, 278], [0, 0, 1, 0, 3, 0, 278], [0, 1, 0, 0, 2, 0, 278], [0, 1, 0, 0, 2, 0, 278], [0, 1, 0, 0, 2, 0, 278], [0, 1, 0, 0, 2, 0, 278], [0, 1, 0, 0, 2, 0, 278], [0, 0, 1, 0, 3, 0, 278], [0, 1, 0, 0, 2, 0, 278], [0, 1, 0, 0, 2, 0, 278], [0, 0, 0, 0, 2, 0, 278], [0, 1, 0, 0, 2, 0, 278], [0, 0, 0, 0, 1, 0, 7], [0, 0, 0, 0, 2, 0, 7], [0, 1, 0, 0, 2, 0, 278], [0, 2, 2, 0, 2, 0, 278], [0, 0, 0, 0, 1, 0, 278], [0, 1, 1, 0, 4, 0, 278], [0, 1, 1, 0, 2, 0, 278], [0, 0, 0, 0, 1, 0, 10], [0, 0, 0, 0, 2, 0, 7], [0, 1, 0, 0, 2, 0, 278], [0, 1, 1, 0, 4, 1, 278], [0, 1, 0, 0, 2, 0, 278], [0, 0, 0, 0, 2, 0, 278], [0, 1, 0, 0, 2, 1, 278], [0, 0, 0, 0, 2, 0, 278], [0, 0, 0, 0, 2, 0, 7], [0, 1, 3, 0, 4, 1, 278], [0, 2, 6, 0, 12, 4, 278], [0, 0, 1, 0, 3, 0, 278], [0, 0, 0, 0, 2, 0, 7], [0, 0, 2, 0, 3, 0, 278], [0, 0, 0, 0, 2, 0, 7], [0, 1, 0, 0, 2, 0, 278], [0, 3, 2, 0, 4, 0, 278], [0, 2, 1, 0, 2, 1, 278], [0, 0, 7, 1, 10, 0, 278], [0, 0, 0, 0, 1, 0, 7], [0, 1, 0, 0, 2, 0, 278], [0, 0, 0, 0, 1, 0, 7], [0, 0, 0, 0, 2, 0, 7], [0, 0, 0, 0, 2, 0, 7], [0, 0, 1, 0, 3, 0, 278], [0, 1, 1, 0, 4, 0, 278], [0, 1, 1, 0, 1, 0, 278], [0, 1, 4, 0, 7, 1, 278], [0, 1, 1, 0, 4, 0, 11], [0, 2, 1, 0, 3, 1, 278], [0, 1, 1, 0, 4, 1, 278], [0, 1, 3, 0, 4, 1, 278], [0, 1, 3, 0, 4, 1, 278], [0, 1, 0, 0, 1, 1, 278], [0, 1, 3, 0, 4, 1, 278], [0, 1, 0, 0, 2, 0, 278], [0, 1, 0, 0, 2, 0, 278], [0, 1, 0, 0, 2, 0, 278], [0, 1, 1, 0, 4, 1, 278], [0, 1, 1, 0, 4, 0, 278], [0, 1, 0, 0, 2, 1, 278], [0, 1, 3, 0, 3, 0, 278], [0, 1, 5, 0, 8, 1, 278], [0, 5, 6, 1, 9, 0, 278], [0, 0, 3, 1, 7, 1, 278], [0, 0, 3, 1, 4, 0, 278], [0, 1, 1, 0, 4, 1, 278], [0, 0, 1, 0, 3, 0, 278], [0, 2, 5, 0, 9, 2, 278], [0, 3, 10, 0, 15, 3, 278], [0, 2, 1, 0, 3, 0, 278], [0, 1, 3, 0, 4, 1, 278], [0, 1, 1, 0, 4, 1, 278], [0, 1, 3, 0, 4, 1, 278], [0, 0, 1, 0, 3, 0, 278], [0, 1, 1, 0, 4, 0, 278], [0, 1, 0, 0, 2, 0, 278], [0, 0, 2, 0, 3, 0, 278], [0, 1, 1, 0, 1, 0, 278], [0, 2, 1, 0, 5, 1, 278], [0, 1, 1, 0, 1, 0, 278], [0, 0, 2, 1, 5, 0, 278], [0, 2, 1, 0, 2, 1, 278], [0, 1, 0, 0, 2, 0, 278], [0, 1, 3, 0, 4, 1, 278], [0, 1, 1, 0, 4, 1, 278], [0, 1, 3, 0, 4, 1, 278], [0, 0, 1, 0, 3, 0, 278], [0, 2, 1, 0, 3, 0, 278], [0, 1, 1, 0, 4, 1, 278], [0, 1, 3, 0, 4, 1, 278], [0, 0, 0, 0, 1, 0, 278], [0, 1, 1, 0, 4, 0, 278], [0, 0, 0, 0, 2, 0, 278], [0, 0, 4, 0, 5, 1, 278], [0, 0, 0, 0, 1, 0, 278], [0, 2, 1, 0, 2, 1, 278], [0, 1, 1, 0, 4, 1, 278], [0, 1, 3, 0, 4, 1, 278], [0, 0, 1, 0, 3, 0, 278], [0, 1, 6, 0, 10, 2, 278], [1, 1, 8, 2, 10, 0, 278], [0, 1, 0, 0, 2, 0, 278], [0, 0, 1, 0, 3, 0, 278], [0, 1, 2, 0, 4, 0, 278], [0, 1, 3, 0, 4, 1, 278], [0, 1, 3, 0, 4, 1, 278], [0, 1, 1, 0, 4, 0, 278], [0, 0, 4, 0, 5, 1, 278], [0, 0, 2, 0, 3, 0, 278], [0, 1, 1, 0, 4, 1, 278], [0, 1, 1, 0, 4, 1, 278], [0, 0, 3, 0, 4, 1, 278], [0, 0, 1, 0, 3, 0, 278], [0, 0, 2, 0, 4, 0, 278], [0, 0, 3, 0, 7, 1, 278], [0, 2, 4, 0, 8, 3, 278], [0, 1, 3, 0, 4, 1, 278], [0, 1, 3, 0, 4, 1, 278], [0, 1, 1, 0, 2, 0, 278], [0, 0, 1, 0, 3, 0, 278], [0, 1, 0, 0, 2, 0, 278], [0, 0, 0, 1, 1, 0, 0], [0, 0, 5, 0, 6, 1, 278], [0, 1, 1, 0, 4, 1, 278], [0, 0, 0, 0, 2, 0, 278], [0, 1, 1, 0, 4, 1, 278], [0, 2, 0, 0, 2, 2, 278], [0, 0, 0, 0, 2, 0, 278], [0, 0, 0, 0, 2, 0, 278], [0, 0, 0, 0, 2, 0, 278], [0, 0, 0, 0, 1, 0, 278], [0, 1, 3, 0, 4, 1, 278], [0, 1, 1, 0, 4, 0, 278], [0, 1, 3, 0, 4, 1, 278], [0, 2, 1, 0, 2, 1, 278], [0, 0, 0, 0, 2, 0, 278], [0, 1, 1, 0, 4, 1, 278], [0, 0, 1, 0, 3, 0, 278], [0, 2, 7, 1, 13, 2, 278], [0, 0, 1, 0, 3, 0, 278], [0, 1, 3, 0, 4, 1, 278], [0, 1, 1, 0, 1, 0, 278], [0, 1, 1, 0, 1, 0, 278], [0, 1, 3, 0, 4, 1, 278], [0, 1, 0, 0, 2, 1, 278], [0, 0, 0, 0, 1, 0, 278], [0, 0, 0, 0, 1, 0, 278], [0, 1, 3, 0, 4, 1, 278], [0, 1, 1, 0, 4, 0, 278], [0, 1, 1, 0, 1, 0, 278], [0, 2, 2, 0, 5, 0, 278], [0, 0, 1, 0, 3, 0, 278], [0, 0, 1, 0, 3, 0, 0], [0, 1, 3, 0, 4, 1, 278], [0, 1, 0, 0, 1, 1, 278], [0, 1, 3, 0, 4, 1, 278]], "fname": "quotearg_buffer_restyled"}
{"n_num": 4, "succs": [[], [0], [0], [1, 2]], "features": [[0, 2, 27, 3, 34, 2, 0], [0, 0, 1, 0, 2, 0, 1], [0, 1, 1, 0, 1, 0, 1], [0, 2, 7, 0, 10, 1, 3]], "fname": "quotearg_buffer"}
{"n_num": 1, "succs": [[]], "features": [[0, 2, 11, 1, 15, 1, 0]], "fname": "quotearg_alloc"}
{"n_num": 6, "succs": [[1, 4], [3], [5], [2, 5], [3], []], "features": [[0, 2, 6, 0, 9, 1, 5], [0, 0, 1, 0, 2, 0, 3], [0, 0, 4, 0, 4, 0, 1], [0, 9, 52, 5, 67, 5, 2], [0, 1, 1, 0, 1, 0, 3], [0, 0, 1, 0, 3, 0, 0]], "fname": "quotearg_alloc_mem"}
{"n_num": 8, "succs": [[], [0, 2], [0], [1], [1, 3], [4, 7], [5], [5]], "features": [[0, 1, 1, 0, 4, 0, 0], [0, 1, 0, 0, 2, 0, 2], [0, 1, 3, 1, 4, 0, 1], [0, 2, 5, 1, 6, 0, 3], [0, 1, 2, 0, 4, 0, 4], [0, 0, 1, 0, 3, 0, 7], [0, 2, 5, 0, 7, 1, 7], [0, 2, 5, 1, 10, 3, 7]], "fname": "quotearg_free"}
{"n_num": 16, "succs": [[11], [0, 11], [14], [2, 14], [13, 6], [4, 15], [8, 9], [1], [10, 7], [], [1], [13], [], [3, 12], [12], []], "features": [[0, 0, 5, 0, 5, 0, 6], [0, 1, 5, 1, 8, 0, 7], [0, 0, 2, 1, 3, 0, 2], [0, 3, 7, 0, 13, 3, 3], [0, 0, 1, 0, 3, 0, 13], [0, 2, 11, 1, 15, 1, 15], [0, 2, 3, 0, 7, 0, 12], [0, 1, 1, 0, 2, 0, 8], [0, 3, 2, 0, 7, 2, 10], [0, 0, 0, 1, 1, 0, 0], [0, 0, 1, 0, 1, 0, 8], [0, 4, 12, 1, 20, 5, 5], [0, 0, 5, 1, 8, 0, 0], [0, 5, 33, 1, 45, 6, 4], [0, 3, 27, 2, 33, 3, 1], [0, 0, 0, 1, 1, 0, 0]], "fname": "quotearg_n_options"}
{"n_num": 1, "succs": [[]], "features": [[0, 3, 9, 1, 13, 1, 0]], "fname": "quotearg_n"}
{"n_num": 1, "succs": [[]], "features": [[0, 2, 10, 1, 14, 1, 0]], "fname": "quotearg_n_mem"}
{"n_num": 1, "succs": [[]], "features": [[0, 2, 6, 1, 10, 1, 0]], "fname": "quotearg"}
{"n_num": 1, "succs": [[]], "features": [[0, 2, 8, 1, 12, 1, 0]], "fname": "quotearg_mem"}
{"n_num": 3, "succs": [[], [0, 2], []], "features": [[0, 0, 0, 1, 1, 0, 0], [0, 2, 18, 2, 24, 1, 2], [0, 0, 0, 0, 2, 0, 0]], "fname": "quotearg_n_style"}
{"n_num": 3, "succs": [[1, 2], [], []], "features": [[0, 1, 18, 2, 24, 1, 2], [0, 0, 0, 0, 2, 0, 0], [0, 0, 0, 1, 1, 0, 0]], "fname": "quotearg_n_style_mem"}
{"n_num": 1, "succs": [[]], "features": [[0, 2, 8, 1, 12, 1, 0]], "fname": "quotearg_style"}
{"n_num": 1, "succs": [[]], "features": [[0, 2, 10, 1, 14, 1, 0]], "fname": "quotearg_style_mem"}
{"n_num": 3, "succs": [[], [0, 2], []], "features": [[0, 0, 0, 1, 1, 0, 0], [0, 3, 33, 2, 39, 1, 2], [0, 0, 0, 0, 2, 0, 0]], "fname": "quotearg_char_mem"}
{"n_num": 1, "succs": [[]], "features": [[0, 2, 9, 1, 13, 1, 0]], "fname": "quotearg_char"}
{"n_num": 1, "succs": [[]], "features": [[0, 2, 6, 1, 10, 1, 0]], "fname": "quotearg_colon"}
{"n_num": 1, "succs": [[]], "features": [[0, 2, 9, 1, 13, 1, 0]], "fname": "quotearg_colon_mem"}
{"n_num": 3, "succs": [[1, 2], [], []], "features": [[0, 4, 36, 3, 43, 1, 2], [0, 0, 0, 0, 2, 0, 0], [0, 0, 0, 1, 1, 0, 0]], "fname": "quotearg_n_style_colon"}
{"n_num": 1, "succs": [[]], "features": [[0, 2, 12, 1, 16, 1, 0]], "fname": "quotearg_n_custom"}
{"n_num": 3, "succs": [[1, 2], [], []], "features": [[0, 1, 34, 2, 40, 1, 2], [0, 0, 0, 0, 2, 0, 0], [0, 0, 0, 1, 1, 0, 0]], "fname": "quotearg_n_custom_mem"}
{"n_num": 1, "succs": [[]], "features": [[0, 2, 10, 1, 14, 1, 0]], "fname": "quotearg_custom"}
{"n_num": 1, "succs": [[]], "features": [[0, 2, 13, 1, 17, 1, 0]], "fname": "quotearg_custom_mem"}
{"n_num": 1, "succs": [[]], "features": [[0, 2, 10, 1, 14, 1, 0]], "fname": "quote_n_mem"}
{"n_num": 1, "succs": [[]], "features": [[0, 2, 8, 1, 12, 1, 0]], "fname": "quote_mem"}
{"n_num": 1, "succs": [[]], "features": [[0, 2, 9, 1, 13, 1, 0]], "fname": "quote_n"}
{"n_num": 1, "succs": [[]], "features": [[0, 2, 6, 1, 10, 1, 0]], "fname": "quote"}
{"n_num": 1, "succs": [[]], "features": [[0, 3, 5, 1, 9, 1, 0]], "fname": "getcon"}
{"n_num": 1, "succs": [[]], "features": [[0, 0, 3, 0, 6, 0, 0]], "fname": "freecon"}
{"n_num": 1, "succs": [[]], "features": [[0, 3, 5, 1, 9, 1, 0]], "fname": "getfscreatecon"}
{"n_num": 1, "succs": [[]], "features": [[0, 3, 5, 1, 9, 1, 0]], "fname": "setfscreatecon"}
{"n_num": 1, "succs": [[]], "features": [[0, 3, 7, 1, 11, 1, 0]], "fname": "matchpathcon"}
{"n_num": 1, "succs": [[]], "features": [[0, 3, 6, 1, 10, 1, 0]], "fname": "getfilecon"}
{"n_num": 1, "succs": [[]], "features": [[0, 3, 6, 1, 10, 1, 0]], "fname": "lgetfilecon"}
{"n_num": 1, "succs": [[]], "features": [[0, 3, 6, 1, 10, 1, 0]], "fname": "fgetfilecon"}
{"n_num": 1, "succs": [[]], "features": [[0, 3, 6, 1, 10, 1, 0]], "fname": "setfilecon"}
{"n_num": 1, "succs": [[]], "features": [[0, 3, 6, 1, 10, 1, 0]], "fname": "lsetfilecon"}
{"n_num": 1, "succs": [[]], "features": [[0, 3, 6, 1, 10, 1, 0]], "fname": "fsetfilecon"}
{"n_num": 1, "succs": [[]], "features": [[0, 3, 5, 1, 9, 1, 0]], "fname": "security_check_context"}
{"n_num": 1, "succs": [[]], "features": [[0, 3, 5, 1, 9, 1, 0]], "fname": "security_check_context_raw"}
{"n_num": 1, "succs": [[]], "features": [[0, 3, 5, 1, 9, 1, 0]], "fname": "setexeccon"}
{"n_num": 1, "succs": [[]], "features": [[0, 3, 9, 1, 13, 1, 0]], "fname": "security_compute_create"}
{"n_num": 1, "succs": [[]], "features": [[0, 3, 5, 1, 9, 1, 0]], "fname": "string_to_security_class"}
{"n_num": 1, "succs": [[]], "features": [[0, 3, 6, 1, 10, 1, 0]], "fname": "matchpathcon_init_prefix"}
{"n_num": 17, "succs": [[16], [0, 4, 5, 6, 7, 8, 12, 13, 14, 15], [16], [1, 2], [16], [16], [16], [16], [16], [10, 11], [3], [3], [16], [], [16], [16], []], "features": [[0, 3, 11, 2, 15, 1, 1], [0, 2, 2, 0, 5, 2, 11], [0, 12, 36, 2, 49, 10, 1], [1, 5, 12, 4, 18, 0, 13], [0, 2, 9, 2, 12, 0, 1], [0, 5, 17, 2, 23, 3, 1], [0, 12, 36, 2, 49, 10, 1], [0, 4, 14, 2, 19, 2, 1], [0, 8, 24, 2, 33, 6, 1], [0, 2, 13, 0, 16, 1, 16], [0, 2, 6, 1, 7, 0, 14], [0, 2, 8, 1, 10, 0, 14], [0, 10, 32, 2, 43, 8, 1], [0, 0, 0, 1, 1, 0, 0], [0, 10, 28, 2, 39, 8, 1], [0, 8, 20, 2, 29, 6, 1], [0, 0, 1, 0, 9, 0, 0]], "fname": "version_etc_arn"}
{"n_num": 4, "succs": [[], [0, 3], [1], [1]], "features": [[0, 0, 9, 1, 13, 0, 0], [0, 0, 4, 0, 7, 1, 3], [0, 2, 8, 0, 10, 1, 3], [0, 1, 0, 0, 1, 1, 3]], "fname": "version_etc_ar"}
{"n_num": 10, "succs": [[], [0, 8], [1, 5], [1, 7], [3], [9, 4], [2], [2], [], [3]], "features": [[0, 0, 0, 0, 2, 0, 0], [0, 0, 10, 1, 14, 0, 2], [0, 1, 0, 0, 2, 0, 9], [0, 0, 5, 0, 7, 0, 9], [0, 0, 10, 0, 12, 1, 9], [0, 1, 2, 0, 4, 0, 9], [0, 2, 10, 0, 13, 1, 9], [0, 1, 0, 0, 1, 1, 9], [0, 0, 0, 1, 1, 0, 0], [0, 0, 5, 0, 5, 0, 9]], "fname": "version_etc_va"}
{"n_num": 5, "succs": [[], [0, 4], [1], [1, 2], []], "features": [[0, 0, 0, 1, 1, 0, 0], [0, 2, 16, 1, 21, 0, 2], [0, 0, 8, 0, 8, 0, 3], [0, 1, 8, 0, 11, 1, 4], [0, 0, 0, 0, 2, 0, 0]], "fname": "version_etc"}
{"n_num": 1, "succs": [[]], "features": [[2, 8, 16, 6, 28, 2, 0]], "fname": "emit_bug_reporting_address"}
{"n_num": 9, "succs": [[3], [0, 3], [8, 7], [2, 4], [], [1, 6], [1], [], []], "features": [[0, 1, 1, 0, 1, 0, 5], [0, 0, 0, 0, 2, 0, 6], [0, 0, 3, 1, 7, 1, 2], [0, 1, 3, 0, 5, 0, 4], [0, 0, 0, 1, 1, 0, 0], [0, 2, 8, 0, 12, 2, 8], [0, 1, 1, 0, 1, 0, 7], [0, 0, 0, 1, 1, 0, 0], [0, 0, 0, 0, 2, 0, 0]], "fname": "xnmalloc"}
{"n_num": 9, "succs": [[], [0, 8], [1, 5], [2, 4], [2], [], [3, 7], [3], []], "features": [[0, 0, 0, 0, 2, 0, 0], [0, 0, 6, 1, 10, 1, 2], [0, 1, 3, 0, 5, 0, 4], [0, 0, 0, 0, 2, 0, 6], [0, 1, 1, 0, 1, 0, 5], [0, 0, 0, 1, 1, 0, 0], [0, 2, 9, 0, 13, 2, 8], [0, 1, 1, 0, 1, 0, 7], [0, 0, 0, 1, 1, 0, 0]], "fname": "xnrealloc"}
{"n_num": 15, "succs": [[], [0, 14], [1], [2, 4], [], [11, 3], [9, 1], [8, 6], [6], [], [13, 7], [10, 12], [10], [7], []], "features": [[0, 0, 0, 0, 2, 0, 0], [0, 0, 9, 1, 13, 1, 2], [0, 2, 4, 0, 7, 3, 3], [0, 2, 2, 0, 5, 1, 5], [0, 0, 0, 1, 1, 0, 0], [0, 2, 10, 0, 14, 1, 14], [0, 1, 3, 0, 5, 0, 4], [0, 0, 0, 0, 2, 0, 6], [0, 1, 1, 0, 1, 0, 5], [0, 0, 0, 1, 1, 0, 0], [0, 1, 2, 0, 4, 1, 8], [0, 1, 0, 0, 2, 0, 10], [0, 3, 4, 0, 8, 2, 9], [0, 1, 1, 0, 1, 0, 7], [0, 0, 0, 1, 1, 0, 0]], "fname": "x2nrealloc"}
{"n_num": 1, "succs": [[]], "features": [[0, 1, 5, 1, 9, 1, 0]], "fname": "xcharalloc"}
{"n_num": 4, "succs": [[2, 3], [0, 3], [], []], "features": [[0, 1, 0, 0, 2, 0, 2], [0, 2, 6, 1, 10, 1, 3], [0, 0, 0, 1, 1, 0, 0], [0, 0, 1, 0, 3, 0, 0]], "fname": "xmalloc"}
{"n_num": 8, "succs": [[4, 6], [0, 2], [0, 3], [7], [5, 6], [], [7], []], "features": [[0, 1, 5, 1, 8, 0, 4], [0, 2, 4, 0, 7, 1, 7], [0, 1, 0, 0, 2, 0, 6], [0, 1, 3, 1, 5, 0, 1], [0, 1, 0, 0, 2, 0, 3], [0, 0, 0, 1, 1, 0, 0], [0, 0, 1, 0, 1, 0, 1], [0, 0, 0, 0, 2, 0, 0]], "fname": "xrealloc"}
{"n_num": 1, "succs": [[]], "features": [[0, 2, 9, 1, 13, 1, 0]], "fname": "x2realloc"}
{"n_num": 1, "succs": [[]], "features": [[0, 2, 10, 2, 15, 1, 0]], "fname": "xzalloc"}
{"n_num": 10, "succs": [[3, 5], [0, 2], [0], [5], [], [4, 6], [4, 7], [8, 9], [], []], "features": [[0, 0, 0, 0, 2, 0, 7], [0, 2, 8, 0, 12, 2, 9], [0, 1, 1, 0, 1, 0, 8], [0, 1, 1, 0, 1, 0, 6], [0, 0, 0, 1, 1, 0, 0], [0, 1, 3, 0, 5, 0, 5], [0, 1, 5, 1, 8, 0, 4], [0, 0, 2, 0, 4, 0, 2], [0, 0, 0, 0, 2, 0, 0], [0, 0, 0, 1, 1, 0, 0]], "fname": "xcalloc"}
{"n_num": 1, "succs": [[]], "features": [[0, 1, 11, 2, 16, 1, 0]], "fname": "xmemdup"}
{"n_num": 1, "succs": [[]], "features": [[0, 1, 9, 2, 14, 1, 0]], "fname": "xstrdup"}
{"n_num": 1, "succs": [[]], "features": [[0, 4, 10, 3, 13, 0, 0]], "fname": "xalloc_die"}
{"n_num": 10, "succs": [[3], [0, 3], [6], [2, 4], [2, 5], [2, 7], [8, 9], [6], [], []], "features": [[0, 0, 2, 0, 2, 0, 8], [0, 2, 8, 0, 12, 1, 9], [0, 0, 1, 0, 1, 0, 3], [0, 1, 6, 1, 9, 0, 7], [0, 1, 0, 0, 2, 0, 6], [0, 2, 1, 1, 5, 0, 5], [0, 0, 1, 0, 3, 0, 2], [0, 1, 7, 0, 8, 0, 3], [0, 0, 0, 1, 1, 0, 0], [0, 0, 0, 0, 2, 0, 0]], "fname": "rpl_mbrtowc"}
{"n_num": 8, "succs": [[2, 7], [0, 4], [0, 6], [], [3], [3], [5], [5]], "features": [[0, 1, 8, 2, 12, 0, 6], [0, 1, 8, 0, 11, 1, 7], [0, 2, 1, 0, 5, 2, 6], [0, 1, 0, 0, 5, 1, 0], [0, 1, 1, 0, 2, 0, 1], [0, 0, 3, 0, 4, 1, 1], [0, 0, 0, 0, 1, 0, 2], [0, 0, 0, 0, 1, 0, 2]], "fname": "c_strcasecmp"}
{"n_num": 9, "succs": [[4, 6], [0, 3], [5], [2, 5], [3, 7], [8], [8], [3, 6], []], "features": [[0, 1, 0, 0, 2, 0, 7], [0, 2, 12, 3, 24, 1, 8], [0, 1, 1, 1, 2, 0, 2], [0, 1, 1, 0, 4, 0, 3], [0, 1, 0, 0, 2, 0, 6], [0, 1, 1, 0, 2, 0, 1], [0, 1, 1, 0, 1, 0, 1], [0, 1, 1, 1, 4, 0, 5], [0, 0, 0, 0, 2, 0, 0]], "fname": "close_stream"}
{"n_num": 5, "succs": [[], [0, 4], [0, 3], [0], [2, 3]], "features": [[0, 0, 1, 0, 3, 0, 0], [0, 4, 8, 1, 12, 1, 4], [1, 0, 3, 1, 6, 0, 2], [0, 1, 1, 0, 1, 0, 1], [1, 0, 3, 1, 6, 0, 3]], "fname": "hard_locale"}
{"n_num": 5, "succs": [[1, 2], [2], [3, 4], [4], []], "features": [[0, 3, 4, 1, 8, 1, 4], [0, 1, 1, 0, 1, 0, 3], [0, 0, 2, 0, 4, 0, 2], [1, 0, 1, 0, 1, 0, 1], [0, 0, 1, 0, 3, 0, 0]], "fname": "locale_charset"}
{"n_num": 10, "succs": [[2, 7], [8, 4], [8, 1], [6], [3, 5], [3], [], [6], [9, 4], [4]], "features": [[0, 4, 8, 1, 12, 1, 9], [0, 3, 5, 2, 9, 0, 6], [0, 0, 2, 1, 5, 0, 7], [0, 0, 1, 0, 1, 0, 1], [0, 1, 3, 1, 6, 0, 3], [0, 1, 4, 1, 5, 0, 2], [0, 0, 0, 0, 2, 0, 0], [0, 0, 2, 1, 4, 0, 1], [0, 0, 2, 1, 5, 0, 5], [0, 0, 2, 1, 3, 0, 4]], "fname": "rpl_fclose"}
{"n_num": 3, "succs": [[1, 2], [], [1]], "features": [[0, 2, 6, 0, 9, 1, 2], [0, 0, 0, 0, 3, 0, 0], [0, 2, 4, 1, 5, 0, 1]], "fname": "clear_ungetc_buffer_preserving_position"}
{"n_num": 5, "succs": [[1, 3], [2, 3], [4], [4], []], "features": [[0, 2, 3, 0, 6, 1, 4], [0, 0, 2, 1, 5, 0, 3], [0, 0, 4, 2, 6, 0, 1], [0, 0, 2, 1, 4, 0, 1], [0, 0, 0, 0, 2, 0, 0]], "fname": "rpl_fflush"}
{"n_num": 8, "succs": [[6], [0, 4], [5, 7], [2, 7], [6], [1, 7], [], [6]], "features": [[0, 1, 1, 0, 2, 0, 1], [0, 1, 8, 2, 12, 0, 3], [0, 0, 4, 0, 6, 0, 6], [0, 1, 9, 0, 12, 1, 7], [0, 2, 10, 0, 11, 0, 1], [0, 0, 2, 0, 4, 0, 5], [0, 0, 0, 0, 2, 0, 0], [0, 0, 5, 1, 6, 0, 1]], "fname": "rpl_fseeko"}
{"n_num": 4, "succs": [[], [0], [0], [1, 2]], "features": [[0, 0, 2, 1, 5, 0, 0], [0, 1, 0, 0, 2, 1, 1], [0, 0, 0, 0, 1, 0, 1], [0, 3, 4, 0, 8, 2, 3]], "fname": "rpl_nl_langinfo"}
{"n_num": 8, "succs": [[3, 5], [0, 7], [], [2], [2], [4, 6], [3], [3, 4]], "features": [[0, 1, 0, 0, 2, 0, 5], [0, 1, 4, 0, 6, 0, 7], [0, 0, 0, 0, 2, 0, 0], [0, 1, 1, 0, 2, 0, 1], [0, 1, 1, 0, 1, 0, 1], [0, 2, 0, 0, 3, 1, 4], [0, 0, 0, 0, 1, 0, 2], [0, 2, 0, 0, 3, 1, 3]], "fname": "c_isalnum"}
{"n_num": 6, "succs": [[2, 3], [0, 2], [5], [5], [1, 3], []], "features": [[0, 2, 0, 0, 3, 1, 3], [0, 1, 0, 0, 2, 0, 4], [0, 1, 1, 0, 2, 0, 1], [0, 1, 1, 0, 1, 0, 1], [0, 1, 4, 0, 6, 0, 5], [0, 0, 0, 0, 2, 0, 0]], "fname": "c_isalpha"}
{"n_num": 4, "succs": [[1, 3], [2], [], [2]], "features": [[0, 2, 4, 0, 7, 1, 3], [0, 1, 1, 0, 1, 0, 1], [0, 0, 0, 0, 2, 0, 0], [0, 1, 1, 0, 2, 0, 1]], "fname": "c_isascii"}
{"n_num": 5, "succs": [[4], [0, 2], [0, 3], [4], []], "features": [[0, 1, 1, 0, 2, 0, 1], [0, 1, 3, 0, 5, 0, 4], [0, 1, 0, 0, 2, 0, 3], [0, 1, 1, 0, 1, 0, 1], [0, 1, 1, 0, 3, 0, 0]], "fname": "c_isblank"}
{"n_num": 6, "succs": [[1, 4], [2, 3], [3, 4], [5], [5], []], "features": [[0, 0, 4, 0, 6, 0, 5], [0, 1, 0, 0, 2, 0, 4], [0, 1, 0, 0, 2, 0, 3], [0, 1, 1, 0, 2, 0, 1], [0, 1, 1, 0, 1, 0, 1], [0, 0, 0, 0, 2, 0, 0]], "fname": "c_iscntrl"}
{"n_num": 4, "succs": [[3], [0, 2], [3], []], "features": [[0, 1, 1, 0, 2, 0, 1], [0, 2, 4, 0, 7, 1, 3], [0, 1, 1, 0, 1, 0, 1], [0, 0, 0, 0, 2, 0, 0]], "fname": "c_isdigit"}
{"n_num": 4, "succs": [[3], [0, 2], [3], []], "features": [[0, 1, 1, 0, 2, 0, 1], [0, 2, 4, 0, 7, 1, 3], [0, 1, 1, 0, 1, 0, 1], [0, 0, 0, 0, 2, 0, 0]], "fname": "c_isgraph"}
{"n_num": 4, "succs": [[3], [0, 2], [3], []], "features": [[0, 1, 1, 0, 2, 0, 1], [0, 2, 4, 0, 7, 1, 3], [0, 1, 1, 0, 1, 0, 1], [0, 0, 0, 0, 2, 0, 0]], "fname": "c_islower"}
{"n_num": 4, "succs": [[3], [0, 2], [3], []], "features": [[0, 1, 1, 0, 2, 0, 1], [0, 2, 4, 0, 7, 1, 3], [0, 1, 1, 0, 1, 0, 1], [0, 0, 0, 0, 2, 0, 0]], "fname": "c_isprint"}
{"n_num": 10, "succs": [[3, 5], [0, 7], [1, 4], [5, 7], [8, 5], [9], [5], [9], [6, 7], []], "features": [[0, 1, 0, 0, 2, 0, 4], [0, 1, 0, 0, 2, 0, 5], [0, 1, 4, 0, 6, 0, 9], [0, 2, 0, 0, 3, 1, 3], [0, 1, 0, 0, 2, 0, 5], [0, 1, 1, 0, 2, 0, 1], [0, 0, 0, 0, 1, 0, 2], [0, 1, 1, 0, 1, 0, 1], [0, 2, 0, 0, 3, 1, 4], [0, 0, 0, 0, 2, 0, 0]], "fname": "c_ispunct"}
{"n_num": 6, "succs": [[1, 4], [2, 3], [3, 4], [5], [5], []], "features": [[0, 1, 4, 0, 6, 0, 5], [0, 1, 0, 0, 2, 0, 4], [0, 1, 0, 0, 2, 0, 3], [0, 1, 1, 0, 2, 0, 1], [0, 1, 1, 0, 1, 0, 1], [0, 0, 0, 0, 2, 0, 0]], "fname": "c_isspace"}
{"n_num": 4, "succs": [[2], [0, 3], [], [2]], "features": [[0, 1, 1, 0, 1, 0, 1], [0, 2, 4, 0, 7, 1, 3], [0, 0, 0, 0, 2, 0, 0], [0, 1, 1, 0, 2, 0, 1]], "fname": "c_isupper"}
{"n_num": 5, "succs": [[4], [0, 3], [1, 3], [4], []], "features": [[0, 1, 1, 0, 2, 0, 1], [0, 0, 2, 0, 3, 0, 3], [0, 2, 4, 0, 7, 1, 4], [0, 1, 1, 0, 1, 0, 1], [0, 0, 0, 0, 2, 0, 0]], "fname": "c_isxdigit"}
{"n_num": 4, "succs": [[], [0], [0], [1, 2]], "features": [[0, 0, 0, 0, 2, 0, 0], [0, 1, 1, 0, 3, 1, 1], [0, 0, 1, 0, 1, 0, 1], [0, 2, 4, 0, 7, 1, 3]], "fname": "c_tolower"}
{"n_num": 4, "succs": [[], [0], [0], [1, 2]], "features": [[0, 0, 0, 0, 2, 0, 0], [0, 1, 1, 0, 3, 1, 1], [0, 0, 1, 0, 1, 0, 1], [0, 2, 4, 0, 7, 1, 3]], "fname": "c_toupper"}
{"n_num": 4, "succs": [[2], [0, 3], [2, 3], []], "features": [[0, 0, 0, 0, 2, 0, 2], [0, 2, 11, 1, 17, 3, 3], [0, 1, 3, 1, 7, 1, 2], [0, 1, 0, 0, 8, 1, 0]], "fname": "__libc_csu_init"}
{"n_num": 1, "succs": [[]], "features": [[0, 0, 0, 0, 1, 0, 0]], "fname": "__libc_csu_fini"}
{"n_num": 4, "succs": [[], [0], [0], [1, 2]], "features": [[0, 0, 0, 0, 0, 0, 0], [0, 0, 1, 0, 3, 0, 1], [0, 0, 0, 0, 3, 0, 1], [0, 0, 1, 0, 3, 0, 3]], "fname": "atexit"}
{"n_num": 2, "succs": [[], [0]], "features": [[0, 0, 0, 0, 0, 0, 0], [0, 1, 3, 0, 4, 0, 1]], "fname": "stat_0"}
{"n_num": 1, "succs": [[]], "features": [[0, 2, 0, 0, 3, 2, 0]], "fname": "term_proc"}
{"n_num": 1, "succs": [[]], "features": [[0, 0, 0, 0, 1, 0, 0]], "fname": "free@@GLIBC_2.2.5"}
{"n_num": 1, "succs": [[]], "features": [[0, 0, 0, 0, 1, 0, 0]], "fname": "abort@@GLIBC_2.2.5"}
{"n_num": 1, "succs": [[]], "features": [[0, 0, 0, 0, 1, 0, 0]], "fname": "__errno_location@@GLIBC_2.2.5"}
{"n_num": 1, "succs": [[]], "features": [[0, 0, 0, 0, 1, 0, 0]], "fname": "strncmp@@GLIBC_2.2.5"}
{"n_num": 1, "succs": [[]], "features": [[0, 0, 0, 0, 1, 0, 0]], "fname": "_exit@@GLIBC_2.2.5"}
{"n_num": 1, "succs": [[]], "features": [[0, 0, 0, 0, 1, 0, 0]], "fname": "__fpending@@GLIBC_2.2.5"}
{"n_num": 1, "succs": [[]], "features": [[0, 0, 0, 0, 1, 0, 0]], "fname": "textdomain@@GLIBC_2.2.5"}
{"n_num": 1, "succs": [[]], "features": [[0, 0, 0, 0, 1, 0, 0]], "fname": "fclose@@GLIBC_2.2.5"}
{"n_num": 1, "succs": [[]], "features": [[0, 0, 0, 0, 1, 0, 0]], "fname": "bindtextdomain@@GLIBC_2.2.5"}
{"n_num": 1, "succs": [[]], "features": [[0, 0, 0, 0, 1, 0, 0]], "fname": "__ctype_get_mb_cur_max@@GLIBC_2.2.5"}
{"n_num": 1, "succs": [[]], "features": [[0, 0, 0, 0, 1, 0, 0]], "fname": "strlen@@GLIBC_2.2.5"}
{"n_num": 1, "succs": [[]], "features": [[0, 0, 0, 0, 1, 0, 0]], "fname": "__stack_chk_fail@@GLIBC_2.4"}
{"n_num": 1, "succs": [[]], "features": [[0, 0, 0, 0, 1, 0, 0]], "fname": "getopt_long@@GLIBC_2.2.5"}
{"n_num": 1, "succs": [[]], "features": [[0, 0, 0, 0, 1, 0, 0]], "fname": "mbrtowc@@GLIBC_2.2.5"}
{"n_num": 1, "succs": [[]], "features": [[0, 0, 0, 0, 1, 0, 0]], "fname": "gettext@@GLIBC_2.2.5"}
{"n_num": 1, "succs": [[]], "features": [[0, 0, 0, 0, 1, 0, 0]], "fname": "printf@@GLIBC_2.2.5"}
{"n_num": 1, "succs": [[]], "features": [[0, 0, 0, 0, 1, 0, 0]], "fname": "strrchr@@GLIBC_2.2.5"}
{"n_num": 1, "succs": [[]], "features": [[0, 0, 0, 0, 1, 0, 0]], "fname": "lseek@@GLIBC_2.2.5"}
{"n_num": 1, "succs": [[]], "features": [[0, 0, 0, 0, 1, 0, 0]], "fname": "memset@@GLIBC_2.2.5"}
{"n_num": 1, "succs": [[]], "features": [[0, 0, 0, 0, 1, 0, 0]], "fname": "__libc_start_main@@GLIBC_2.2.5"}
{"n_num": 1, "succs": [[]], "features": [[0, 0, 0, 0, 1, 0, 0]], "fname": "memcmp@@GLIBC_2.2.5"}
{"n_num": 1, "succs": [[]], "features": [[0, 0, 0, 0, 1, 0, 0]], "fname": "fputs_unlocked@@GLIBC_2.2.5"}
{"n_num": 1, "succs": [[]], "features": [[0, 0, 0, 0, 1, 0, 0]], "fname": "ferror_unlocked@@GLIBC_2.2.5"}
{"n_num": 1, "succs": [[]], "features": [[0, 0, 0, 0, 1, 0, 0]], "fname": "calloc@@GLIBC_2.2.5"}
{"n_num": 1, "succs": [[]], "features": [[0, 0, 0, 0, 1, 0, 0]], "fname": "strcmp@@GLIBC_2.2.5"}
{"n_num": 1, "succs": [[]], "features": [[0, 0, 0, 0, 1, 0, 0]], "fname": "fprintf@@GLIBC_2.2.5"}
{"n_num": 1, "succs": [[]], "features": [[0, 0, 0, 0, 1, 0, 0]], "fname": "mkfifo@@GLIBC_2.2.5"}
{"n_num": 1, "succs": [[]], "features": [[0, 0, 0, 0, 1, 0, 0]], "fname": "umask@@GLIBC_2.2.5"}
{"n_num": 1, "succs": [[]], "features": [[0, 0, 0, 0, 1, 0, 0]], "fname": "memcpy@@GLIBC_2.14"}
{"n_num": 1, "succs": [[]], "features": [[0, 0, 0, 0, 1, 0, 0]], "fname": "fileno@@GLIBC_2.2.5"}
{"n_num": 1, "succs": [[]], "features": [[0, 0, 0, 0, 1, 0, 0]], "fname": "__xstat@@GLIBC_2.2.5"}
{"n_num": 1, "succs": [[]], "features": [[0, 0, 0, 0, 1, 0, 0]], "fname": "malloc@@GLIBC_2.2.5"}
{"n_num": 1, "succs": [[]], "features": [[0, 0, 0, 0, 1, 0, 0]], "fname": "fflush@@GLIBC_2.2.5"}
{"n_num": 1, "succs": [[]], "features": [[0, 0, 0, 0, 1, 0, 0]], "fname": "nl_langinfo@@GLIBC_2.2.5"}
{"n_num": 1, "succs": [[]], "features": [[0, 0, 0, 0, 1, 0, 0]], "fname": "__freading@@GLIBC_2.2.5"}
{"n_num": 1, "succs": [[]], "features": [[0, 0, 0, 0, 1, 0, 0]], "fname": "realloc@@GLIBC_2.2.5"}
{"n_num": 1, "succs": [[]], "features": [[0, 0, 0, 0, 1, 0, 0]], "fname": "setlocale@@GLIBC_2.2.5"}
{"n_num": 1, "succs": [[]], "features": [[0, 0, 0, 0, 1, 0, 0]], "fname": "chmod@@GLIBC_2.2.5"}
{"n_num": 1, "succs": [[]], "features": [[0, 0, 0, 0, 1, 0, 0]], "fname": "error@@GLIBC_2.2.5"}
{"n_num": 1, "succs": [[]], "features": [[0, 0, 0, 0, 1, 0, 0]], "fname": "fseeko@@GLIBC_2.2.5"}
{"n_num": 1, "succs": [[]], "features": [[0, 0, 0, 0, 1, 0, 0]], "fname": "__cxa_atexit@@GLIBC_2.2.5"}
{"n_num": 1, "succs": [[]], "features": [[0, 0, 0, 0, 1, 0, 0]], "fname": "exit@@GLIBC_2.2.5"}
{"n_num": 1, "succs": [[]], "features": [[0, 0, 0, 0, 1, 0, 0]], "fname": "fwrite@@GLIBC_2.2.5"}
{"n_num": 1, "succs": [[]], "features": [[0, 0, 0, 0, 1, 0, 0]], "fname": "mbsinit@@GLIBC_2.2.5"}
{"n_num": 1, "succs": [[]], "features": [[0, 0, 0, 0, 1, 0, 0]], "fname": "iswprint@@GLIBC_2.2.5"}
{"n_num": 1, "succs": [[]], "features": [[0, 0, 0, 0, 1, 0, 0]], "fname": "__ctype_b_loc@@GLIBC_2.3"}
{"n_num": 1, "succs": [[]], "features": [[0, 0, 0, 0, 1, 0, 0]], "fname": "free"}
{"n_num": 1, "succs": [[]], "features": [[0, 0, 0, 0, 1, 0, 0]], "fname": "abort"}
{"n_num": 1, "succs": [[]], "features": [[0, 0, 0, 0, 1, 0, 0]], "fname": "__errno_location"}
{"n_num": 1, "succs": [[]], "features": [[0, 0, 0, 0, 1, 0, 0]], "fname": "strncmp"}
{"n_num": 1, "succs": [[]], "features": [[0, 0, 0, 0, 1, 0, 0]], "fname": "_exit"}
{"n_num": 1, "succs": [[]], "features": [[0, 0, 0, 0, 1, 0, 0]], "fname": "__fpending"}
{"n_num": 1, "succs": [[]], "features": [[0, 0, 0, 0, 1, 0, 0]], "fname": "textdomain"}
{"n_num": 1, "succs": [[]], "features": [[0, 0, 0, 0, 1, 0, 0]], "fname": "fclose"}
{"n_num": 1, "succs": [[]], "features": [[0, 0, 0, 0, 1, 0, 0]], "fname": "bindtextdomain"}
{"n_num": 1, "succs": [[]], "features": [[0, 0, 0, 0, 1, 0, 0]], "fname": "__ctype_get_mb_cur_max"}
{"n_num": 1, "succs": [[]], "features": [[0, 0, 0, 0, 1, 0, 0]], "fname": "strlen"}
{"n_num": 1, "succs": [[]], "features": [[0, 0, 0, 0, 1, 0, 0]], "fname": "__stack_chk_fail"}
{"n_num": 1, "succs": [[]], "features": [[0, 0, 0, 0, 1, 0, 0]], "fname": "getopt_long"}
{"n_num": 1, "succs": [[]], "features": [[0, 0, 0, 0, 1, 0, 0]], "fname": "mbrtowc"}
{"n_num": 1, "succs": [[]], "features": [[0, 0, 0, 0, 1, 0, 0]], "fname": "gettext"}
{"n_num": 1, "succs": [[]], "features": [[0, 0, 0, 0, 1, 0, 0]], "fname": "printf"}
{"n_num": 1, "succs": [[]], "features": [[0, 0, 0, 0, 1, 0, 0]], "fname": "strrchr"}
{"n_num": 1, "succs": [[]], "features": [[0, 0, 0, 0, 1, 0, 0]], "fname": "lseek"}
{"n_num": 1, "succs": [[]], "features": [[0, 0, 0, 0, 1, 0, 0]], "fname": "memset"}
{"n_num": 1, "succs": [[]], "features": [[0, 0, 0, 0, 1, 0, 0]], "fname": "__libc_start_main"}
{"n_num": 1, "succs": [[]], "features": [[0, 0, 0, 0, 1, 0, 0]], "fname": "memcmp"}
{"n_num": 1, "succs": [[]], "features": [[0, 0, 0, 0, 1, 0, 0]], "fname": "fputs_unlocked"}
{"n_num": 1, "succs": [[]], "features": [[0, 0, 0, 0, 1, 0, 0]], "fname": "ferror_unlocked"}
{"n_num": 1, "succs": [[]], "features": [[0, 0, 0, 0, 1, 0, 0]], "fname": "calloc"}
{"n_num": 1, "succs": [[]], "features": [[0, 0, 0, 0, 1, 0, 0]], "fname": "strcmp"}
{"n_num": 1, "succs": [[]], "features": [[0, 0, 0, 0, 1, 0, 0]], "fname": "fprintf"}
{"n_num": 1, "succs": [[]], "features": [[0, 0, 0, 0, 1, 0, 0]], "fname": "mkfifo"}
{"n_num": 1, "succs": [[]], "features": [[0, 0, 0, 0, 1, 0, 0]], "fname": "umask"}
{"n_num": 1, "succs": [[]], "features": [[0, 0, 0, 0, 1, 0, 0]], "fname": "memcpy"}
{"n_num": 1, "succs": [[]], "features": [[0, 0, 0, 0, 1, 0, 0]], "fname": "fileno"}
{"n_num": 1, "succs": [[]], "features": [[0, 0, 0, 0, 1, 0, 0]], "fname": "__xstat"}
{"n_num": 1, "succs": [[]], "features": [[0, 0, 0, 0, 1, 0, 0]], "fname": "malloc"}
{"n_num": 1, "succs": [[]], "features": [[0, 0, 0, 0, 1, 0, 0]], "fname": "fflush"}
{"n_num": 1, "succs": [[]], "features": [[0, 0, 0, 0, 1, 0, 0]], "fname": "nl_langinfo"}
{"n_num": 1, "succs": [[]], "features": [[0, 0, 0, 0, 1, 0, 0]], "fname": "__freading"}
{"n_num": 1, "succs": [[]], "features": [[0, 0, 0, 0, 1, 0, 0]], "fname": "realloc"}
{"n_num": 1, "succs": [[]], "features": [[0, 0, 0, 0, 1, 0, 0]], "fname": "setlocale"}
{"n_num": 1, "succs": [[]], "features": [[0, 0, 0, 0, 1, 0, 0]], "fname": "chmod"}
{"n_num": 1, "succs": [[]], "features": [[0, 0, 0, 0, 1, 0, 0]], "fname": "error"}
{"n_num": 1, "succs": [[]], "features": [[0, 0, 0, 0, 1, 0, 0]], "fname": "fseeko"}
{"n_num": 1, "succs": [[]], "features": [[0, 0, 0, 0, 1, 0, 0]], "fname": "__cxa_atexit"}
{"n_num": 1, "succs": [[]], "features": [[0, 0, 0, 0, 1, 0, 0]], "fname": "exit"}
{"n_num": 1, "succs": [[]], "features": [[0, 0, 0, 0, 1, 0, 0]], "fname": "fwrite"}
{"n_num": 1, "succs": [[]], "features": [[0, 0, 0, 0, 1, 0, 0]], "fname": "mbsinit"}
{"n_num": 1, "succs": [[]], "features": [[0, 0, 0, 0, 1, 0, 0]], "fname": "iswprint"}
{"n_num": 1, "succs": [[]], "features": [[0, 0, 0, 0, 1, 0, 0]], "fname": "__ctype_b_loc"}
